{
  "tiles": [
    {
      "id": 0,
      "title": "Percent Ring",
      "description": "% of Something",
      "data": "70",
      "color": "orange",
      "height": "",
      "width": ""
    },
    {
      "id": 1,
      "title": "Bar Chart",
      "description": "This is a bar chart",
      "data": [ 
        {
          "key": "Hello World 1",
          "values": [
            { 
              "label" : "A Label",
              "color": "#554662",
              "value" : 29
            }, 
            { 
              "label" : "B Label",
              "color": "#554662", 
              "value" : 13
            }, 
            { 
              "label" : "C Label",
              "color": "#554662", 
              "value" : 4
            }, 
            { 
              "label" : "D Label",
              "color": "#554662", 
              "value" : 30
            }, 
            { 
              "label" : "E Label",
              "color": "#554662",
              "value" : 10
            }
          ]
        }
      ],
      "color": "purple",
      "height": "",
      "width": ""
    },
    {
      "id": 2,
      "title": "Pie Chart",
      "description": "% of each",
      "data": [
        { 
          "label": "One",
          "value" : 29.765957771107
        } , 
        {
          "label": "Two",
          "value" : 0
        } , 
        { 
          "label": "Three",
          "value" : 32.807804682612
        } , 
        { 
          "label": "Four",
          "value" : 196.45946739256
        } , 
        { 
          "label": "Five",
          "value" : 0.19434030906893
        } , 
        { 
          "label": "Six",
          "value" : 98.079782601442
        } , 
        { 
          "label": "Seven",
          "value" : 13.925743130903
        } , 
        { 
          "label": "Eight",
          "value" : 5.1387322875705
        }
      ],
      "color": "green",
      "height": "",
      "width": ""
    },
    {
      "id": 3,
      "title": "Table",
      "description": "this is a table",
      "data": {
        "headers": [
          {
            "dataid": "id",
            "alias": "ID"
          },
          {
            "dataid": "name",
            "alias": "Name"
          },
          {
            "dataid": "info",
            "alias": "Information"
          }
        ],
        "values": [
          { 
            "id": "0",
            "name": "Item 0",
            "info": "This is Item 0"
          },
          { 
            "id": "1",
            "name": "Item 1",
            "info": "This is Item 1"
          },
          { 
            "id": "2",
            "name": "Item 2",
            "info": "This is Item 2"
          },
          { 
            "id": "3",
            "name": "Item 3",
            "info": "This is Item 3"
          },
          { 
            "id": "4",
            "name": "Item 4",
            "info": "This is Item 4"
          },
          { 
            "id": "5",
            "name": "Item 5",
            "info": "This is Item 5"
          },
          { 
            "id": "6",
            "name": "Item 6",
            "info": "This is Item 6"
          },
          { 
            "id": "7",
            "name": "Item 7",
            "info": "This is Item 7"
          },
          { 
            "id": "8",
            "name": "Item 8",
            "info": "This is Item 8"
          }
        ]
      },
      "color": "blue",
      "height": "",
      "width": ""
    },
    {
      "id": 4,
      "title": "Line Chart",
      "description": "This is a line chart",
      "data": [ 
        {
          "key": "Line",
          "color": "#FF5533",
          "values": [
            {
              "x": 0,
              "y": 0
            },
            {
              "x": 1,
              "y": 1
            },
            {
              "x": 2,
              "y": 2
            },
            {
              "x": 3,
              "y": 3
            },
            {
              "x": 4,
              "y": 2
            },
            {
              "x": 5,
              "y": 0
            },
            {
              "x": 6,
              "y": 4
            },
            {
              "x": 7,
              "y": 2
            },
            {
              "x": 8,
              "y": 3
            },
            {
              "x": 9,
              "y": 3
            },
            {
              "x": 10,
              "y": 2
            }
          ]
        }
      ],
      "color": "red",
      "height": "",
      "width": ""
    }
  ]
}